huckleberry_cli/__init__.py
huckleberry_cli/cli.py
huckleberry_cli-0.1.1.dist-info/METADATA
huckleberry_cli-0.1.1.dist-info/WHEEL
huckleberry_cli-0.1.1.dist-info/entry_points.txt
huckleberry_cli-0.1.1.dist-info/licenses/LICENSE
huckleberry_cli-0.1.1.dist-info/RECORD
