Metadata-Version: 2.4
Name: huckleberry-cli
Version: 0.1.1
Summary: CLI for Huckleberry baby tracking
Project-URL: Homepage, https://github.com/jayhickey/huckleberry-cli
Project-URL: Repository, https://github.com/jayhickey/huckleberry-cli
Author: Jay Hickey
License-Expression: MIT
License-File: LICENSE
Requires-Python: >=3.11
Requires-Dist: huckleberry-api
Provides-Extra: dev
Requires-Dist: pytest>=7.0.0; extra == 'dev'
Requires-Dist: ruff>=0.1.1; extra == 'dev'
